{"mc":{"10":{"events":{},"frames":[{"y":-193,"res":"w0001","x":-77},{"y":-186,"res":"w0005","x":-40},{"y":-241,"res":"w0009","x":-44},{"y":-467,"res":"w0015","x":-204},{"y":-531,"res":"w0016","x":-145},{"y":-417,"res":"w0017","x":-132},{"y":-426,"res":"w0018","x":-149},{"y":-434,"res":"w0019","x":-249},{"y":-441,"res":"w0020","x":-253},{"y":-446,"res":"w0021","x":-253},{"y":-448,"res":"w0023","x":-253},{"y":-448,"res":"w0024","x":-117},{"y":-456,"res":"w0025","x":-147},{"y":-534,"res":"w0029","x":-178},{"y":-452,"res":"w0039","x":-251},{"y":-476,"res":"w0040","x":-190},{"y":-491,"res":"w0041","x":-178},{"y":-473,"res":"w0042","x":-53},{"y":-223,"res":"w0043","x":-28},{"y":-104,"res":"w0044","x":-27},{"y":-193,"res":"w0053","x":-77}],"labels":{"frame":1,"name":10,"end":21},"frameRate":8}},"res":{"w0001":{"x":0,"y":0,"w":154,"h":245},"w0015":{"x":437,"y":0,"w":282,"h":484},"w0016":{"x":719,"y":0,"w":230,"h":548},"w0017":{"x":949,"y":0,"w":330,"h":462},"w0044":{"x":340,"y":1639,"w":271,"h":124},"w0040":{"x":899,"y":1091,"w":294,"h":493},"w0023":{"x":1400,"y":548,"w":354,"h":529},"w0021":{"x":1050,"y":548,"w":350,"h":470},"w0053":{"x":611,"y":1639,"w":154,"h":245},"w0019":{"x":344,"y":548,"w":353,"h":513},"w0039":{"x":539,"y":1091,"w":360,"h":469},"w0043":{"x":0,"y":1639,"w":340,"h":242},"w0009":{"x":307,"y":0,"w":130,"h":259},"w0005":{"x":154,"y":0,"w":153,"h":214},"w0029":{"x":293,"y":1091,"w":246,"h":548},"w0042":{"x":1559,"y":1091,"w":337,"h":491},"w0025":{"x":0,"y":1091,"w":293,"h":471},"w0020":{"x":697,"y":548,"w":353,"h":483},"w0018":{"x":0,"y":548,"w":344,"h":531},"w0024":{"x":1754,"y":548,"w":272,"h":543},"w0041":{"x":1193,"y":1091,"w":366,"h":507}}}