{"file":"1.png","mc":{"anim":{"events":[],"frameRate":24,"frames":[{"duration":6,"res":"1","x":-649,"y":-649},{"duration":2,"res":"2","x":-227,"y":-382},{"duration":1,"res":"3","x":-228,"y":-424},{"duration":1,"res":"4","x":-224,"y":-419},{"duration":1,"res":"5","x":-218,"y":-426},{"duration":2,"res":"6","x":-214,"y":-436},{"duration":2,"res":"7","x":-201,"y":-448},{"duration":2,"res":"8","x":-145,"y":-451},{"duration":2,"res":"9","x":-100,"y":-456},{"duration":2,"res":"10","x":-93,"y":-459},{"duration":2,"res":"11","x":-95,"y":-462},{"duration":2,"res":"12","x":-97,"y":-465},{"duration":2,"res":"13","x":-97,"y":-468},{"duration":2,"res":"14","x":-100,"y":-471},{"duration":2,"res":"15","x":-100,"y":-472},{"duration":2,"res":"16","x":-98,"y":-474},{"duration":2,"res":"17","x":-12,"y":-384},{"duration":2,"res":"18","x":22,"y":-220},{"duration":2,"res":"19","x":-649,"y":-649},{"duration":2,"res":"20","x":-649,"y":-649},{"duration":2,"res":"21","x":-649,"y":-649},{"duration":2,"res":"22","x":-649,"y":-649},{"duration":2,"res":"23","x":-649,"y":-649},{"duration":2,"res":"24","x":-649,"y":-649},{"duration":2,"res":"25","x":-649,"y":-649},{"duration":2,"res":"26","x":-649,"y":-649},{"duration":2,"res":"27","x":-649,"y":-649},{"duration":2,"res":"28","x":-649,"y":-649},{"duration":2,"res":"29","x":-649,"y":-649},{"duration":2,"res":"30","x":-649,"y":-649},{"duration":2,"res":"31","x":-649,"y":-649},{"duration":2,"res":"32","x":-649,"y":-649}],"labels":[{"end":32,"frame":1,"name":"0"}]}},"res":{"1":{"h":1,"w":1,"x":2,"y":880},"10":{"h":406,"w":216,"x":2,"y":468},"11":{"h":344,"w":220,"x":1160,"y":458},"12":{"h":350,"w":224,"x":934,"y":458},"13":{"h":354,"w":226,"x":706,"y":466},"14":{"h":256,"w":130,"x":1784,"y":594},"15":{"h":256,"w":130,"x":1784,"y":336},"16":{"h":256,"w":128,"x":1916,"y":336},"17":{"h":166,"w":38,"x":1704,"y":2},"18":{"h":2,"w":4,"x":2,"y":876},"19":{"h":1,"w":1,"x":2,"y":880},"2":{"h":332,"w":230,"x":1784,"y":2},"20":{"h":1,"w":1,"x":2,"y":880},"21":{"h":1,"w":1,"x":2,"y":880},"22":{"h":1,"w":1,"x":2,"y":880},"23":{"h":1,"w":1,"x":2,"y":880},"24":{"h":1,"w":1,"x":2,"y":880},"25":{"h":1,"w":1,"x":2,"y":880},"26":{"h":1,"w":1,"x":2,"y":880},"27":{"h":1,"w":1,"x":2,"y":880},"28":{"h":1,"w":1,"x":2,"y":880},"29":{"h":1,"w":1,"x":2,"y":880},"3":{"h":442,"w":400,"x":1382,"y":454},"30":{"h":1,"w":1,"x":2,"y":880},"31":{"h":1,"w":1,"x":2,"y":880},"32":{"h":1,"w":1,"x":2,"y":880},"4":{"h":454,"w":426,"x":832,"y":2},"5":{"h":450,"w":442,"x":1260,"y":2},"6":{"h":462,"w":428,"x":402,"y":2},"7":{"h":464,"w":398,"x":2,"y":2},"8":{"h":390,"w":262,"x":442,"y":466},"9":{"h":396,"w":220,"x":220,"y":468}}}